{
    "schema_version": "v1",
    "name_for_human": "Local File Access",
    "name_for_model": "local_file_access",
    "description_for_human": "A plugin that allows GPT to use the CLI, Python, and edit files.",
    "description_for_model": "Plugin to control a computer via CLI, Python, and editing files.",
    "auth": {
      "type": "none"
    },
    "api": {
      "type": "openapi",
      "url": "http://localhost:5010/api.yaml"
    },
    "contact_email": "legal@example.com",
    "legal_info_url": "http://example.com/legal"
  }
  
